tupa123/__init__.py
tupa123/tupa123.py
tupa123-1.0.7.data/data/LICENSE.txt
tupa123-1.0.7.dist-info/LICENSE.txt
tupa123-1.0.7.dist-info/METADATA
tupa123-1.0.7.dist-info/WHEEL
tupa123-1.0.7.dist-info/top_level.txt
tupa123-1.0.7.dist-info/RECORD
