Metadata-Version: 2.1
Name: tupa123
Version: 1.0.7
Summary: fully connected neural network with four layers
Author: Leandro Schemmer
Author-email: leandro.schemmer@gmail.com
License: MIT
License-File: LICENSE.txt
Requires-Dist: numpy (>=1.23.5)
Requires-Dist: matplotlib (>=3.6.3)
Requires-Dist: pandas (>=1.5.3)
